{"collection_length":810,"Doge Capital #18":{"rank":723},"Doge Capital #54":{"rank":386},"Doge Capital #2487":{"rank":317},"Doge Capital #3561":{"rank":740},"Doge Capital #2306":{"rank":782},"Doge Capital #4950":{"rank":714},"Doge Capital #4030":{"rank":572},"Doge Capital #295":{"rank":695},"Doge Capital #1685":{"rank":508},"Doge Capital #1049":{"rank":701},"Doge Capital #565":{"rank":770},"Doge Capital #372":{"rank":654},"Doge Capital #2640":{"rank":602},"Doge Capital #4032":{"rank":392},"Doge Capital #1806":{"rank":342},"Doge Capital #3080":{"rank":573},"Doge Capital #1425":{"rank":379},"Doge Capital #1803":{"rank":416},"Doge Capital #4235":{"rank":567},"Doge Capital #12":{"rank":795},"Doge Capital #3618":{"rank":758},"Doge Capital #700":{"rank":193},"Doge Capital #3796":{"rank":426},"Doge Capital #1800":{"rank":135},"Doge Capital #509":{"rank":550},"Doge Capital #179":{"rank":363},"Doge Capital #4003":{"rank":412},"Doge Capital #4675":{"rank":536},"Doge Capital #1026":{"rank":597},"Doge Capital #3466":{"rank":318},"Doge Capital #1430":{"rank":514},"Doge Capital #2630":{"rank":562},"Doge Capital #2142":{"rank":596},"Doge Capital #3260":{"rank":126},"Doge Capital #1862":{"rank":564},"Doge Capital #942":{"rank":271},"Doge Capital #4233":{"rank":600},"Doge Capital #779":{"rank":777},"Doge Capital #4774":{"rank":473},"Doge Capital #4267":{"rank":122},"Doge Capital #2228":{"rank":221},"Doge Capital #4566":{"rank":298},"Doge Capital #492":{"rank":157},"Doge Capital #4817":{"rank":268},"Doge Capital #2496":{"rank":309},"Doge Capital #3978":{"rank":487},"Doge Capital #2949":{"rank":417},"Doge Capital #1699":{"rank":601},"Doge Capital #889":{"rank":100},"Doge Capital #3769":{"rank":320},"Doge Capital #2774":{"rank":716},"Doge Capital #727":{"rank":182},"Doge Capital #3698":{"rank":292},"Doge Capital #846":{"rank":334},"Doge Capital #4833":{"rank":485},"Doge Capital #2529":{"rank":516},"Doge Capital #4539":{"rank":455},"Doge Capital #4248":{"rank":391},"Doge Capital #4028":{"rank":427},"Doge Capital #2508":{"rank":301},"Doge Capital #1267":{"rank":130},"Doge Capital #943":{"rank":285},"Doge Capital #1503":{"rank":768},"Doge Capital #3207":{"rank":152},"Doge Capital #1230":{"rank":635},"Doge Capital #1484":{"rank":378},"Doge Capital #359":{"rank":437},"Doge Capital #2416":{"rank":162},"Doge Capital #2891":{"rank":472},"Doge Capital #311":{"rank":25},"Doge Capital #1383":{"rank":706},"Doge Capital #3608":{"rank":519},"Doge Capital #2394":{"rank":83},"Doge Capital #2400":{"rank":532},"Doge Capital #2563":{"rank":520},"Doge Capital #724":{"rank":418},"Doge Capital #1848":{"rank":338},"Doge Capital #4245":{"rank":442},"Doge Capital #2985":{"rank":230},"Doge Capital #1216":{"rank":241},"Doge Capital #1770":{"rank":501},"Doge Capital #2085":{"rank":250},"Doge Capital #3739":{"rank":720},"Doge Capital #2173":{"rank":641},"Doge Capital #4290":{"rank":345},"Doge Capital #850":{"rank":254},"Doge Capital #1701":{"rank":385},"Doge Capital #4693":{"rank":247},"Doge Capital #4401":{"rank":111},"Doge Capital #4806":{"rank":101},"Doge Capital #3034":{"rank":304},"Doge Capital #4931":{"rank":449},"Doge Capital #2415":{"rank":558},"Doge Capital #872":{"rank":305},"Doge Capital #2087":{"rank":793},"Doge Capital #572":{"rank":211},"Doge Capital #2879":{"rank":724},"Doge Capital #759":{"rank":84},"Doge Capital #1674":{"rank":204},"Doge Capital #3703":{"rank":155},"Doge Capital #4831":{"rank":313},"Doge Capital #3283":{"rank":560},"Doge Capital #156":{"rank":295},"Doge Capital #4885":{"rank":42},"Doge Capital #4335":{"rank":745},"Doge Capital #2016":{"rank":336},"Doge Capital #2006":{"rank":129},"Doge Capital #3408":{"rank":225},"Doge Capital #2489":{"rank":281},"Doge Capital #730":{"rank":13},"Doge Capital #1931":{"rank":299},"Doge Capital #845":{"rank":104},"Doge Capital #3654":{"rank":267},"Doge Capital #2099":{"rank":434},"Doge Capital #415":{"rank":258},"Doge Capital #1150":{"rank":790},"Doge Capital #2810":{"rank":694},"Doge Capital #3992":{"rank":775},"Doge Capital #2841":{"rank":421},"Doge Capital #2392":{"rank":474},"Doge Capital #125":{"rank":515},"Doge Capital #472":{"rank":63},"Doge Capital #3086":{"rank":368},"Doge Capital #4213":{"rank":206},"Doge Capital #1119":{"rank":118},"Doge Capital #633":{"rank":639},"Doge Capital #3912":{"rank":364},"Doge Capital #3859":{"rank":214},"Doge Capital #4951":{"rank":93},"Doge Capital #4260":{"rank":57},"Doge Capital #4034":{"rank":168},"Doge Capital #2291":{"rank":666},"Doge Capital #3657":{"rank":87},"Doge Capital #505":{"rank":339},"Doge Capital #1399":{"rank":28},"Doge Capital #1697":{"rank":248},"Doge Capital #4320":{"rank":92},"Doge Capital #2638":{"rank":283},"Doge Capital #3952":{"rank":156},"Doge Capital #3678":{"rank":228},"Doge Capital #2479":{"rank":266},"Doge Capital #2112":{"rank":629},"Doge Capital #4322":{"rank":585},"Doge Capital #338":{"rank":21},"Doge Capital #3428":{"rank":612},"Doge Capital #4232":{"rank":107},"Doge Capital #2553":{"rank":333},"Doge Capital #2569":{"rank":121},"Doge Capital #2819":{"rank":2},"Doge Capital #3322":{"rank":147},"Doge Capital #340":{"rank":495},"Doge Capital #4568":{"rank":488},"Doge Capital #2065":{"rank":90},"Doge Capital #1562":{"rank":384},"Doge Capital #2987":{"rank":607},"Doge Capital #638":{"rank":808},"Doge Capital #2104":{"rank":587},"Doge Capital #64":{"rank":6},"Doge Capital #1512":{"rank":115},"Doge Capital #2909":{"rank":65},"Doge Capital #2970":{"rank":289},"Doge Capital #1145":{"rank":12},"Doge Capital #2669":{"rank":19},"Doge Capital #4426":{"rank":579},"Doge Capital #2295":{"rank":50},"Doge Capital #1074":{"rank":323},"Doge Capital #2029":{"rank":185},"Doge Capital #2259":{"rank":496},"Doge Capital #1309":{"rank":410},"Doge Capital #3692":{"rank":518},"Doge Capital #1282":{"rank":88},"Doge Capital #407":{"rank":260},"Doge Capital #3098":{"rank":343},"Doge Capital #3030":{"rank":45},"Doge Capital #2019":{"rank":438},"Doge Capital #2017":{"rank":180},"Doge Capital #683":{"rank":762},"Doge Capital #1645":{"rank":212},"Doge Capital #1886":{"rank":73},"Doge Capital #4315":{"rank":682},"Doge Capital #3066":{"rank":29},"Doge Capital #2441":{"rank":18},"Doge Capital #4937":{"rank":34},"Doge Capital #1152":{"rank":26},"Doge Capital #2459":{"rank":5},"Doge Capital #1666":{"rank":77},"Doge Capital #431":{"rank":810},"Doge Capital #1183":{"rank":48},"Doge Capital #1549":{"rank":138},"Doge Capital #3567":{"rank":4},"Doge Capital #1795":{"rank":20},"Doge Capital #3772":{"rank":89},"Doge Capital #911":{"rank":798},"Doge Capital #2615":{"rank":64},"Doge Capital #3380":{"rank":235},"Doge Capital #3848":{"rank":747},"Doge Capital #4934":{"rank":296},"Doge Capital #2867":{"rank":322},"Doge Capital #4247":{"rank":264},"Doge Capital #641":{"rank":332},"Doge Capital #2859":{"rank":94},"Doge Capital #1550":{"rank":8},"Doge Capital #2120":{"rank":530},"Doge Capital #186":{"rank":800},"Doge Capital #2784":{"rank":71},"Doge Capital #3297":{"rank":463},"Doge Capital #1359":{"rank":141},"Doge Capital #4293":{"rank":226},"Doge Capital #1728":{"rank":263},"Doge Capital #1956":{"rank":252},"Doge Capital #1824":{"rank":616},"Doge Capital #858":{"rank":776},"Doge Capital #328":{"rank":580},"Doge Capital #3793":{"rank":144},"Doge Capital #3004":{"rank":783},"Doge Capital #2211":{"rank":196},"Doge Capital #4536":{"rank":373},"Doge Capital #4026":{"rank":177},"Doge Capital #3219":{"rank":671},"Doge Capital #2283":{"rank":269},"Doge Capital #283":{"rank":408},"Doge Capital #2426":{"rank":582},"Doge Capital #3549":{"rank":233},"Doge Capital #271":{"rank":236},"Doge Capital #2433":{"rank":131},"Doge Capital #1304":{"rank":476},"Doge Capital #4062":{"rank":290},"Doge Capital #1407":{"rank":529},"Doge Capital #400":{"rank":197},"Doge Capital #2304":{"rank":669},"Doge Capital #4391":{"rank":356},"Doge Capital #1615":{"rank":275},"Doge Capital #2796":{"rank":553},"Doge Capital #4624":{"rank":500},"Doge Capital #710":{"rank":594},"Doge Capital #3235":{"rank":146},"Doge Capital #1224":{"rank":650},"Doge Capital #4512":{"rank":399},"Doge Capital #4740":{"rank":402},"Doge Capital #4274":{"rank":372},"Doge Capital #4656":{"rank":213},"Doge Capital #292":{"rank":727},"Doge Capital #4689":{"rank":456},"Doge Capital #2202":{"rank":557},"Doge Capital #2945":{"rank":702},"Doge Capital #83":{"rank":328},"Doge Capital #1385":{"rank":659},"Doge Capital #3496":{"rank":142},"Doge Capital #4067":{"rank":738},"Doge Capital #2538":{"rank":614},"Doge Capital #2575":{"rank":685},"Doge Capital #3975":{"rank":432},"Doge Capital #2580":{"rank":56},"Doge Capital #2412":{"rank":170},"Doge Capital #3688":{"rank":750},"Doge Capital #4862":{"rank":699},"Doge Capital #2214":{"rank":493},"Doge Capital #649":{"rank":689},"Doge Capital #2767":{"rank":240},"Doge Capital #3752":{"rank":69},"Doge Capital #3171":{"rank":446},"Doge Capital #3112":{"rank":788},"Doge Capital #4772":{"rank":741},"Doge Capital #1505":{"rank":549},"Doge Capital #3961":{"rank":175},"Doge Capital #4808":{"rank":291},"Doge Capital #708":{"rank":559},"Doge Capital #4530":{"rank":80},"Doge Capital #1018":{"rank":611},"Doge Capital #2635":{"rank":95},"Doge Capital #3863":{"rank":406},"Doge Capital #470":{"rank":732},"Doge Capital #1041":{"rank":551},"Doge Capital #2883":{"rank":640},"Doge Capital #3822":{"rank":655},"Doge Capital #3367":{"rank":686},"Doge Capital #1083":{"rank":478},"Doge Capital #2234":{"rank":273},"Doge Capital #4256":{"rank":578},"Doge Capital #987":{"rank":486},"Doge Capital #47":{"rank":774},"Doge Capital #4545":{"rank":608},"Doge Capital #3658":{"rank":749},"Doge Capital #1095":{"rank":492},"Doge Capital #3899":{"rank":181},"Doge Capital #2209":{"rank":286},"Doge Capital #3728":{"rank":148},"Doge Capital #4717":{"rank":308},"Doge Capital #2072":{"rank":431},"Doge Capital #4905":{"rank":371},"Doge Capital #2222":{"rank":617},"Doge Capital #3490":{"rank":284},"Doge Capital #3041":{"rank":347},"Doge Capital #224":{"rank":191},"Doge Capital #266":{"rank":380},"Doge Capital #563":{"rank":760},"Doge Capital #4679":{"rank":674},"Doge Capital #66":{"rank":35},"Doge Capital #1456":{"rank":667},"Doge Capital #396":{"rank":739},"Doge Capital #2047":{"rank":546},"Doge Capital #2193":{"rank":613},"Doge Capital #1256":{"rank":722},"Doge Capital #1283":{"rank":179},"Doge Capital #4311":{"rank":350},"Doge Capital #1647":{"rank":729},"Doge Capital #2516":{"rank":105},"Doge Capital #1350":{"rank":590},"Doge Capital #740":{"rank":259},"Doge Capital #452":{"rank":785},"Doge Capital #893":{"rank":593},"Doge Capital #1953":{"rank":644},"Doge Capital #3881":{"rank":625},"Doge Capital #4917":{"rank":459},"Doge Capital #1818":{"rank":154},"Doge Capital #2507":{"rank":335},"Doge Capital #3862":{"rank":513},"Doge Capital #4930":{"rank":623},"Doge Capital #3801":{"rank":721},"Doge Capital #1328":{"rank":765},"Doge Capital #1677":{"rank":494},"Doge Capital #387":{"rank":201},"Doge Capital #2532":{"rank":433},"Doge Capital #1781":{"rank":253},"Doge Capital #1238":{"rank":807},"Doge Capital #579":{"rank":321},"Doge Capital #3009":{"rank":319},"Doge Capital #3050":{"rank":352},"Doge Capital #1159":{"rank":375},"Doge Capital #3102":{"rank":278},"Doge Capital #4434":{"rank":401},"Doge Capital #402":{"rank":30},"Doge Capital #1270":{"rank":117},"Doge Capital #1233":{"rank":55},"Doge Capital #2717":{"rank":151},"Doge Capital #3155":{"rank":353},"Doge Capital #2946":{"rank":538},"Doge Capital #144":{"rank":367},"Doge Capital #2637":{"rank":171},"Doge Capital #4636":{"rank":678},"Doge Capital #2191":{"rank":114},"Doge Capital #584":{"rank":54},"Doge Capital #2130":{"rank":340},"Doge Capital #2061":{"rank":563},"Doge Capital #1424":{"rank":294},"Doge Capital #4979":{"rank":603},"Doge Capital #1888":{"rank":756},"Doge Capital #2427":{"rank":7},"Doge Capital #1182":{"rank":159},"Doge Capital #1855":{"rank":447},"Doge Capital #1885":{"rank":40},"Doge Capital #2401":{"rank":393},"Doge Capital #3259":{"rank":569},"Doge Capital #2714":{"rank":422},"Doge Capital #2181":{"rank":772},"Doge Capital #4208":{"rank":677},"Doge Capital #3836":{"rank":535},"Doge Capital #1500":{"rank":198},"Doge Capital #3124":{"rank":661},"Doge Capital #3053":{"rank":482},"Doge Capital #1352":{"rank":15},"Doge Capital #3282":{"rank":22},"Doge Capital #3329":{"rank":31},"Doge Capital #1944":{"rank":466},"Doge Capital #2349":{"rank":665},"Doge Capital #1034":{"rank":730},"Doge Capital #2560":{"rank":150},"Doge Capital #2703":{"rank":183},"Doge Capital #3705":{"rank":792},"Doge Capital #3544":{"rank":70},"Doge Capital #449":{"rank":725},"Doge Capital #3048":{"rank":303},"Doge Capital #3199":{"rank":184},"Doge Capital #2971":{"rank":548},"Doge Capital #281":{"rank":534},"Doge Capital #1154":{"rank":217},"Doge Capital #2161":{"rank":631},"Doge Capital #1372":{"rank":592},"Doge Capital #1531":{"rank":624},"Doge Capital #2152":{"rank":272},"Doge Capital #4895":{"rank":325},"Doge Capital #2590":{"rank":210},"Doge Capital #3096":{"rank":11},"Doge Capital #3393":{"rank":331},"Doge Capital #3909":{"rank":16},"Doge Capital #2348":{"rank":86},"Doge Capital #963":{"rank":189},"Doge Capital #3192":{"rank":398},"Doge Capital #2313":{"rank":314},"Doge Capital #2007":{"rank":652},"Doge Capital #1812":{"rank":113},"Doge Capital #2694":{"rank":784},"Doge Capital #2711":{"rank":605},"Doge Capital #1858":{"rank":66},"Doge Capital #1753":{"rank":809},"Doge Capital #2180":{"rank":67},"Doge Capital #2537":{"rank":10},"Doge Capital #4367":{"rank":163},"Doge Capital #4446":{"rank":78},"Doge Capital #2747":{"rank":244},"Doge Capital #3245":{"rank":223},"Doge Capital #741":{"rank":366},"Doge Capital #4810":{"rank":481},"Doge Capital #3890":{"rank":124},"Doge Capital #1478":{"rank":439},"Doge Capital #898":{"rank":545},"Doge Capital #2366":{"rank":169},"Doge Capital #2552":{"rank":120},"Doge Capital #4182":{"rank":166},"Doge Capital #836":{"rank":396},"Doge Capital #522":{"rank":61},"Doge Capital #991":{"rank":329},"Doge Capital #4021":{"rank":460},"Doge Capital #3234":{"rank":561},"Doge Capital #3925":{"rank":376},"Doge Capital #2325":{"rank":134},"Doge Capital #115":{"rank":748},"Doge Capital #278":{"rank":209},"Doge Capital #3840":{"rank":544},"Doge Capital #2641":{"rank":628},"Doge Capital #2075":{"rank":349},"Doge Capital #2977":{"rank":638},"Doge Capital #1630":{"rank":91},"Doge Capital #4148":{"rank":480},"Doge Capital #1153":{"rank":1},"Doge Capital #4898":{"rank":112},"Doge Capital #2290":{"rank":711},"Doge Capital #3504":{"rank":664},"Doge Capital #1012":{"rank":717},"Doge Capital #3121":{"rank":381},"Doge Capital #2530":{"rank":82},"Doge Capital #2217":{"rank":216},"Doge Capital #2307":{"rank":407},"Doge Capital #3445":{"rank":779},"Doge Capital #3573":{"rank":662},"Doge Capital #2725":{"rank":369},"Doge Capital #3790":{"rank":413},"Doge Capital #4161":{"rank":622},"Doge Capital #947":{"rank":97},"Doge Capital #1529":{"rank":746},"Doge Capital #4374":{"rank":428},"Doge Capital #2514":{"rank":764},"Doge Capital #78":{"rank":354},"Doge Capital #1295":{"rank":499},"Doge Capital #3296":{"rank":277},"Doge Capital #790":{"rank":374},"Doge Capital #3364":{"rank":575},"Doge Capital #2582":{"rank":660},"Doge Capital #2440":{"rank":731},"Doge Capital #682":{"rank":733},"Doge Capital #2280":{"rank":232},"Doge Capital #2461":{"rank":744},"Doge Capital #1507":{"rank":312},"Doge Capital #3809":{"rank":696},"Doge Capital #2691":{"rank":763},"Doge Capital #2498":{"rank":804},"Doge Capital #1396":{"rank":293},"Doge Capital #1441":{"rank":348},"Doge Capital #2627":{"rank":330},"Doge Capital #2998":{"rank":96},"Doge Capital #2644":{"rank":504},"Doge Capital #4172":{"rank":791},"Doge Capital #3833":{"rank":708},"Doge Capital #1830":{"rank":205},"Doge Capital #1527":{"rank":510},"Doge Capital #3716":{"rank":158},"Doge Capital #927":{"rank":675},"Doge Capital #3777":{"rank":458},"Doge Capital #3505":{"rank":178},"Doge Capital #4953":{"rank":176},"Doge Capital #564":{"rank":174},"Doge Capital #1810":{"rank":786},"Doge Capital #1890":{"rank":187},"Doge Capital #2424":{"rank":110},"Doge Capital #3638":{"rank":76},"Doge Capital #3026":{"rank":509},"Doge Capital #1031":{"rank":541},"Doge Capital #1838":{"rank":555},"Doge Capital #2836":{"rank":554},"Doge Capital #2190":{"rank":761},"Doge Capital #1050":{"rank":621},"Doge Capital #967":{"rank":218},"Doge Capital #554":{"rank":737},"Doge Capital #3882":{"rank":693},"Doge Capital #2892":{"rank":506},"Doge Capital #2131":{"rank":754},"Doge Capital #1394":{"rank":475},"Doge Capital #2488":{"rank":355},"Doge Capital #3424":{"rank":781},"Doge Capital #2868":{"rank":44},"Doge Capital #3464":{"rank":436},"Doge Capital #662":{"rank":464},"Doge Capital #2215":{"rank":387},"Doge Capital #3254":{"rank":457},"Doge Capital #2321":{"rank":274},"Doge Capital #1508":{"rank":539},"Doge Capital #192":{"rank":58},"Doge Capital #3459":{"rank":687},"Doge Capital #937":{"rank":672},"Doge Capital #2864":{"rank":526},"Doge Capital #1070":{"rank":161},"Doge Capital #2302":{"rank":389},"Doge Capital #497":{"rank":41},"Doge Capital #2015":{"rank":145},"Doge Capital #350":{"rank":668},"Doge Capital #1577":{"rank":419},"Doge Capital #2186":{"rank":649},"Doge Capital #1084":{"rank":287},"Doge Capital #2897":{"rank":658},"Doge Capital #3390":{"rank":249},"Doge Capital #3008":{"rank":705},"Doge Capital #514":{"rank":778},"Doge Capital #172":{"rank":167},"Doge Capital #751":{"rank":591},"Doge Capital #2874":{"rank":139},"Doge Capital #3156":{"rank":794},"Doge Capital #2442":{"rank":262},"Doge Capital #2936":{"rank":642},"Doge Capital #3891":{"rank":648},"Doge Capital #3405":{"rank":700},"Doge Capital #1622":{"rank":220},"Doge Capital #1901":{"rank":735},"Doge Capital #1967":{"rank":429},"Doge Capital #364":{"rank":503},"Doge Capital #1884":{"rank":256},"Doge Capital #3651":{"rank":397},"Doge Capital #2379":{"rank":511},"Doge Capital #3921":{"rank":280},"Doge Capital #1187":{"rank":282},"Doge Capital #2594":{"rank":752},"Doge Capital #2027":{"rank":577},"Doge Capital #3817":{"rank":288},"Doge Capital #2408":{"rank":681},"Doge Capital #3609":{"rank":736},"Doge Capital #631":{"rank":484},"Doge Capital #1327":{"rank":525},"Doge Capital #1520":{"rank":521},"Doge Capital #3145":{"rank":424},"Doge Capital #3373":{"rank":656},"Doge Capital #1602":{"rank":692},"Doge Capital #1608":{"rank":703},"Doge Capital #3091":{"rank":570},"Doge Capital #3029":{"rank":507},"Doge Capital #3854":{"rank":451},"Doge Capital #4835":{"rank":409},"Doge Capital #132":{"rank":316},"Doge Capital #233":{"rank":710},"Doge Capital #3353":{"rank":440},"Doge Capital #491":{"rank":425},"Doge Capital #57":{"rank":657},"Doge Capital #1344":{"rank":133},"Doge Capital #4122":{"rank":257},"Doge Capital #309":{"rank":222},"Doge Capital #640":{"rank":630},"Doge Capital #4970":{"rank":227},"Doge Capital #3631":{"rank":300},"Doge Capital #3067":{"rank":471},"Doge Capital #1568":{"rank":38},"Doge Capital #2815":{"rank":85},"Doge Capital #265":{"rank":527},"Doge Capital #877":{"rank":444},"Doge Capital #3945":{"rank":537},"Doge Capital #3337":{"rank":448},"Doge Capital #717":{"rank":362},"Doge Capital #1185":{"rank":759},"Doge Capital #26":{"rank":188},"Doge Capital #4769":{"rank":773},"Doge Capital #4177":{"rank":238},"Doge Capital #4690":{"rank":326},"Doge Capital #3998":{"rank":679},"Doge Capital #1718":{"rank":805},"Doge Capital #109":{"rank":636},"Doge Capital #781":{"rank":697},"Doge Capital #1651":{"rank":395},"Doge Capital #507":{"rank":574},"Doge Capital #570":{"rank":653},"Doge Capital #4448":{"rank":255},"Doge Capital #2155":{"rank":543},"Doge Capital #885":{"rank":453},"Doge Capital #3922":{"rank":540},"Doge Capital #1178":{"rank":461},"Doge Capital #1506":{"rank":609},"Doge Capital #4745":{"rank":502},"Doge Capital #395":{"rank":462},"Doge Capital #3786":{"rank":62},"Doge Capital #3399":{"rank":36},"Doge Capital #4696":{"rank":522},"Doge Capital #4747":{"rank":490},"Doge Capital #315":{"rank":477},"Doge Capital #390":{"rank":531},"Doge Capital #1938":{"rank":229},"Doge Capital #4631":{"rank":137},"Doge Capital #2086":{"rank":53},"Doge Capital #1382":{"rank":688},"Doge Capital #536":{"rank":556},"Doge Capital #3123":{"rank":766},"Doge Capital #2791":{"rank":60},"Doge Capital #4782":{"rank":452},"Doge Capital #373":{"rank":99},"Doge Capital #2568":{"rank":542},"Doge Capital #1225":{"rank":242},"Doge Capital #2618":{"rank":465},"Doge Capital #3":{"rank":239},"Doge Capital #1521":{"rank":127},"Doge Capital #3443":{"rank":200},"Doge Capital #1903":{"rank":195},"Doge Capital #3115":{"rank":79},"Doge Capital #308":{"rank":24},"Doge Capital #2577":{"rank":72},"Doge Capital #3680":{"rank":797},"Doge Capital #3242":{"rank":194},"Doge Capital #3328":{"rank":173},"Doge Capital #2011":{"rank":106},"Doge Capital #2375":{"rank":3},"Doge Capital #1909":{"rank":566},"Doge Capital #1713":{"rank":160},"Doge Capital #3378":{"rank":469},"Doge Capital #1001":{"rank":132},"Doge Capital #2365":{"rank":327},"Doge Capital #886":{"rank":9},"Doge Capital #1221":{"rank":215},"Doge Capital #860":{"rank":806},"Doge Capital #4074":{"rank":589},"Doge Capital #2059":{"rank":75},"Doge Capital #1715":{"rank":43},"Doge Capital #994":{"rank":361},"Doge Capital #3878":{"rank":753},"Doge Capital #1746":{"rank":707},"Doge Capital #4912":{"rank":360},"Doge Capital #1604":{"rank":98},"Doge Capital #487":{"rank":789},"Doge Capital #1064":{"rank":297},"Doge Capital #4913":{"rank":202},"Doge Capital #2188":{"rank":632},"Doge Capital #699":{"rank":690},"Doge Capital #4513":{"rank":405},"Doge Capital #1906":{"rank":251},"Doge Capital #2919":{"rank":128},"Doge Capital #3020":{"rank":190},"Doge Capital #3980":{"rank":359},"Doge Capital #4255":{"rank":341},"Doge Capital #769":{"rank":307},"Doge Capital #4276":{"rank":802},"Doge Capital #1077":{"rank":49},"Doge Capital #2555":{"rank":125},"Doge Capital #4873":{"rank":246},"Doge Capital #3719":{"rank":108},"Doge Capital #337":{"rank":420},"Doge Capital #3918":{"rank":358},"Doge Capital #4652":{"rank":265},"Doge Capital #433":{"rank":604},"Doge Capital #1489":{"rank":483},"Doge Capital #1071":{"rank":524},"Doge Capital #4355":{"rank":23},"Doge Capital #4419":{"rank":306},"Doge Capital #1409":{"rank":586},"Doge Capital #4364":{"rank":411},"Doge Capital #3846":{"rank":803},"Doge Capital #2446":{"rank":404},"Doge Capital #4805":{"rank":742},"Doge Capital #1057":{"rank":595},"Doge Capital #287":{"rank":712},"Doge Capital #3643":{"rank":489},"Doge Capital #3028":{"rank":626},"Doge Capital #2267":{"rank":315},"Doge Capital #2260":{"rank":203},"Doge Capital #4649":{"rank":606},"Doge Capital #2451":{"rank":709},"Doge Capital #4618":{"rank":116},"Doge Capital #4521":{"rank":454},"Doge Capital #2003":{"rank":598},"Doge Capital #1217":{"rank":103},"Doge Capital #1528":{"rank":683},"Doge Capital #4297":{"rank":123},"Doge Capital #3183":{"rank":234},"Doge Capital #2651":{"rank":270},"Doge Capital #2992":{"rank":365},"Doge Capital #1696":{"rank":571},"Doge Capital #3673":{"rank":143},"Doge Capital #2565":{"rank":588},"Doge Capital #4368":{"rank":634},"Doge Capital #1321":{"rank":310},"Doge Capital #2350":{"rank":208},"Doge Capital #4216":{"rank":39},"Doge Capital #2802":{"rank":382},"Doge Capital #4165":{"rank":68},"Doge Capital #870":{"rank":74},"Doge Capital #737":{"rank":224},"Doge Capital #2544":{"rank":81},"Doge Capital #2030":{"rank":140},"Doge Capital #1184":{"rank":769},"Doge Capital #1016":{"rank":261},"Doge Capital #1850":{"rank":651},"Doge Capital #4443":{"rank":136},"Doge Capital #1946":{"rank":199},"Doge Capital #1163":{"rank":243},"Doge Capital #1281":{"rank":17},"Doge Capital #3805":{"rank":102},"Doge Capital #659":{"rank":684},"Doge Capital #1263":{"rank":33},"Doge Capital #3520":{"rank":14},"Doge Capital #502":{"rank":357},"Doge Capital #2924":{"rank":445},"Doge Capital #3745":{"rank":599},"Doge Capital #3021":{"rank":186},"Doge Capital #3082":{"rank":663},"Doge Capital #2511":{"rank":346},"Doge Capital #3358":{"rank":164},"Doge Capital #644":{"rank":726},"Doge Capital #2670":{"rank":219},"Doge Capital #2351":{"rank":467},"Doge Capital #1075":{"rank":771},"Doge Capital #4803":{"rank":673},"Doge Capital #4754":{"rank":390},"Doge Capital #1322":{"rank":680},"Doge Capital #3132":{"rank":403},"Doge Capital #4804":{"rank":620},"Doge Capital #1665":{"rank":713},"Doge Capital #1963":{"rank":344},"Doge Capital #1811":{"rank":743},"Doge Capital #3686":{"rank":568},"Doge Capital #1148":{"rank":755},"Doge Capital #1523":{"rank":468},"Doge Capital #797":{"rank":691},"Doge Capital #2292":{"rank":491},"Doge Capital #3603":{"rank":383},"Doge Capital #2262":{"rank":276},"Doge Capital #2420":{"rank":801},"Doge Capital #4571":{"rank":565},"Doge Capital #2709":{"rank":728},"Doge Capital #2656":{"rank":400},"Doge Capital #4856":{"rank":32},"Doge Capital #280":{"rank":27},"Doge Capital #2624":{"rank":676},"Doge Capital #2110":{"rank":698},"Doge Capital #926":{"rank":528},"Doge Capital #3398":{"rank":351},"Doge Capital #306":{"rank":734},"Doge Capital #1849":{"rank":119},"Doge Capital #104":{"rank":523},"Doge Capital #821":{"rank":441},"Doge Capital #3236":{"rank":207},"Doge Capital #3288":{"rank":767},"Doge Capital #3886":{"rank":647},"Doge Capital #4900":{"rank":719},"Doge Capital #831":{"rank":780},"Doge Capital #3126":{"rank":388},"Doge Capital #4551":{"rank":450},"Doge Capital #4438":{"rank":109},"Doge Capital #1287":{"rank":619},"Doge Capital #842":{"rank":799},"Doge Capital #2706":{"rank":165},"Doge Capital #4554":{"rank":470},"Doge Capital #3806":{"rank":47},"Doge Capital #1068":{"rank":751},"Doge Capital #3281":{"rank":51},"Doge Capital #979":{"rank":237},"Doge Capital #3252":{"rank":192},"Doge Capital #2462":{"rank":149},"Doge Capital #3055":{"rank":443},"Doge Capital #4984":{"rank":479},"Doge Capital #768":{"rank":581},"Doge Capital #3789":{"rank":633},"Doge Capital #3110":{"rank":547},"Doge Capital #2840":{"rank":415},"Doge Capital #728":{"rank":153},"Doge Capital #4625":{"rank":505},"Doge Capital #1984":{"rank":645},"Doge Capital #1614":{"rank":643},"Doge Capital #2672":{"rank":718},"Doge Capital #3645":{"rank":311},"Doge Capital #1366":{"rank":435},"Doge Capital #1237":{"rank":52},"Doge Capital #114":{"rank":377},"Doge Capital #2808":{"rank":231},"Doge Capital #2702":{"rank":584},"Doge Capital #4045":{"rank":337},"Doge Capital #3845":{"rank":757},"Doge Capital #2610":{"rank":370},"Doge Capital #4628":{"rank":430},"Doge Capital #3161":{"rank":627},"Doge Capital #2299":{"rank":576},"Doge Capital #4294":{"rank":46},"Doge Capital #1172":{"rank":497},"Doge Capital #2243":{"rank":787},"Doge Capital #1218":{"rank":704},"Doge Capital #2619":{"rank":59},"Doge Capital #617":{"rank":583},"Doge Capital #3206":{"rank":552},"Doge Capital #2940":{"rank":615},"Doge Capital #2608":{"rank":279},"Doge Capital #3181":{"rank":324},"Doge Capital #4207":{"rank":618},"Doge Capital #4501":{"rank":637},"Doge Capital #1476":{"rank":512},"Doge Capital #84":{"rank":610},"Doge Capital #4735":{"rank":302},"Doge Capital #4357":{"rank":517},"Doge Capital #4008":{"rank":172},"Doge Capital #1585":{"rank":533},"Doge Capital #896":{"rank":423},"Doge Capital #3025":{"rank":245},"Doge Capital #804":{"rank":37},"Doge Capital #3512":{"rank":498},"Doge Capital #546":{"rank":394},"Doge Capital #2964":{"rank":670},"Doge Capital #39":{"rank":796},"Doge Capital #948":{"rank":715},"Doge Capital #2795":{"rank":646},"Doge Capital #2025":{"rank":414}}